bilibili_video_info_mcp/__init__.py
bilibili_video_info_mcp/__main__.py
bilibili_video_info_mcp/bilibili_api.py
bilibili_video_info_mcp/server.py
iflow_mcp_bilibili_video_info_mcp-0.2.0.dist-info/licenses/LICENSE
iflow_mcp_bilibili_video_info_mcp-0.2.0.dist-info/METADATA
iflow_mcp_bilibili_video_info_mcp-0.2.0.dist-info/WHEEL
iflow_mcp_bilibili_video_info_mcp-0.2.0.dist-info/entry_points.txt
iflow_mcp_bilibili_video_info_mcp-0.2.0.dist-info/top_level.txt
iflow_mcp_bilibili_video_info_mcp-0.2.0.dist-info/RECORD
