Metadata-Version: 2.4
Name: iflow-mcp_bilibili-video-info-mcp
Version: 0.2.0
Summary: An MCP server to fetch Bilibili video information like subtitles, comments, and danmaku.
Author: lesir
Requires-Python: >=3.10
License-File: LICENSE
Requires-Dist: mcp[cli]>=1.11.0
Requires-Dist: requests
Dynamic: license-file
